setup.py
benny/__init__.py
benny/client.py
benny.py.egg-info/PKG-INFO
benny.py.egg-info/SOURCES.txt
benny.py.egg-info/dependency_links.txt
benny.py.egg-info/top_level.txt
benny/utils/__init__.py
benny/utils/fml.py
benny/utils/image.py